langdetector/__init__.py
langdetector/cli.py
langdetector/detect.py
language_detection_nlp-0.0.0.dist-info/licenses/LICENSE
language_detection_nlp-0.0.0.dist-info/METADATA
language_detection_nlp-0.0.0.dist-info/WHEEL
language_detection_nlp-0.0.0.dist-info/entry_points.txt
language_detection_nlp-0.0.0.dist-info/top_level.txt
language_detection_nlp-0.0.0.dist-info/RECORD
