Metadata-Version: 2.4
Name: language-detection-nlp
Version: 0.0.0
Summary: Tiny examples and utilities for language detection
Home-page: https://github.com/swaranika27nath-spec/language-detection-nlp
Author: (your name)
License: MIT
Classifier: Programming Language :: Python :: 3
Classifier: License :: OSI Approved :: MIT License
Classifier: Operating System :: OS Independent
License-File: LICENSE
Dynamic: license-file
